pyats/results/__init__.py
pyats/results/context.cpython-313-darwin.so
pyats/results/counter.cpython-313-darwin.so
pyats/results/result.cpython-313-darwin.so
pyats.results-25.9.dist-info/METADATA
pyats.results-25.9.dist-info/WHEEL
pyats.results-25.9.dist-info/top_level.txt
pyats.results-25.9.dist-info/RECORD
